{
    "version": "1.0.11",
    "architecture": {
        "64bit": {
            "url": "https://github.com/vngcloud/gnab-releases/releases/download/v1.0.11/gnab_1.0.11_windows_amd64.zip",
            "bin": [
                "gnab.exe"
            ],
            "hash": "9153cb9d3ae1965e4f1aaacfe62d7b8d7dfee9f966ca4ebc81eb3bf5306aad4d"
        },
        "arm64": {
            "url": "https://github.com/vngcloud/gnab-releases/releases/download/v1.0.11/gnab_1.0.11_windows_arm64.zip",
            "bin": [
                "gnab.exe"
            ],
            "hash": "03bebdbdd21aa44244e7da8e72448047a66e2b75250c4c55ca3240209b638f28"
        }
    },
    "homepage": "https://github.com/vngcloud/gnab-releases",
    "license": "MIT",
    "description": "GreenNode AgentBase CLI"
}
