{
    "version": "1.0.9",
    "architecture": {
        "64bit": {
            "url": "https://github.com/vngcloud/gnab-releases/releases/download/v1.0.9/gnab_1.0.9_windows_amd64.zip",
            "bin": [
                "gnab.exe"
            ],
            "hash": "62179483ed6c5e974b759bcc87a5609afee8ca53b3119f76e2bb51ffc1587fcc"
        },
        "arm64": {
            "url": "https://github.com/vngcloud/gnab-releases/releases/download/v1.0.9/gnab_1.0.9_windows_arm64.zip",
            "bin": [
                "gnab.exe"
            ],
            "hash": "2dd23797095452314969a9380aa7c37f8b92d340ad980fea2cf1544d5aae8aa0"
        }
    },
    "homepage": "https://github.com/vngcloud/gnab-releases",
    "license": "MIT",
    "description": "GreenNode AgentBase CLI"
}
